pygroebner/__init__.py
pygroebner/base_algebra.py
pygroebner/mymath.py
pygroebner/pygroebner.py
pygroebner-0.0.2.dist-info/LICENSE
pygroebner-0.0.2.dist-info/METADATA
pygroebner-0.0.2.dist-info/WHEEL
pygroebner-0.0.2.dist-info/top_level.txt
pygroebner-0.0.2.dist-info/RECORD
