Metadata-Version: 2.1
Name: pygroebner
Version: 0.0.2
Summary: A package for groebner basis over prime 2 written implemented in python
Home-page: https://github.com/WayneLin92/pygroebner
Author: Weinan Lin
Author-email: lwnpku2015@gmail.com
License: UNKNOWN
Project-URL: Bug Tracker, https://github.com/WayneLin92/pygroebner/issues
Platform: UNKNOWN
Classifier: Programming Language :: Python :: 3
Classifier: License :: OSI Approved :: MIT License
Classifier: Operating System :: OS Independent
Requires-Python: >=3.7
License-File: LICENSE
